{
    "foods": [
        {
            "id": "1",
            "name": "Margherita Pizza",
            "description": "Classic pizza with tomato sauce, mozzarella, and fresh basil",
            "price": 12.99,
            "discountPrice": 9.99,
            "imageUrl": "https://images.unsplash.com/photo-1574071318508-1cdbab80d002?w=400",
            "category": "pizza",
            "isAvailable": true,
            "stockQuantity": 35000,
            "createdAt": "2024-01-15T10:00:00Z",
            "updatedAt": null,
            "quantityUnit": "g"
        },
        {
            "id": "2",
            "name": "Pepperoni Pizza",
            "description": "Pizza topped with pepperoni and mozzarella cheese",
            "price": 14.99,
            "discountPrice": null,
            "imageUrl": "https://images.unsplash.com/photo-1628840042765-356cda07504e?w=400",
            "category": "pizza",
            "isAvailable": true,
            "stockQuantity": 21000,
            "createdAt": "2024-01-15T10:05:00Z",
            "updatedAt": null,
            "quantityUnit": "g"
        },
        {
            "id": "3",
            "name": "Caesar Salad",
            "description": "Fresh romaine lettuce with Caesar dressing, croutons, and parmesan",
            "price": 8.99,
            "discountPrice": null,
            "imageUrl": "https://images.unsplash.com/photo-1546793665-c74683f339c1?w=400",
            "category": "salad",
            "isAvailable": true,
            "stockQuantity": 28000,
            "createdAt": "2024-01-15T10:10:00Z",
            "updatedAt": null,
            "quantityUnit": "g"
        },
        {
            "id": "4",
            "name": "Grilled Chicken Burger",
            "description": "Juicy grilled chicken breast with lettuce, tomato, and special sauce",
            "price": 11.99,
            "discountPrice": 8.99,
            "imageUrl": "https://images.unsplash.com/photo-1606755962773-d324e0a13086?w=400",
            "category": "burger",
            "isAvailable": true,
            "stockQuantity": 11200,
            "createdAt": "2024-01-15T10:15:00Z",
            "updatedAt": null,
            "quantityUnit": "g"
        },
        {
            "id": "5",
            "name": "Chocolate Brownie",
            "description": "Rich chocolate brownie with vanilla ice cream",
            "price": 6.99,
            "discountPrice": null,
            "imageUrl": "https://images.unsplash.com/photo-1606313564200-e75d5e30476c?w=400",
            "category": "dessert",
            "isAvailable": true,
            "stockQuantity": 10800,
            "createdAt": "2024-01-15T10:20:00Z",
            "updatedAt": null,
            "quantityUnit": "g"
        },
        {
            "id": "6",
            "name": "Pasta Carbonara",
            "description": "Creamy pasta with bacon, eggs, and parmesan cheese",
            "price": 13.99,
            "discountPrice": null,
            "imageUrl": "https://images.unsplash.com/photo-1621996346565-e3dbc646d9a9?w=400",
            "category": "pasta",
            "isAvailable": false,
            "stockQuantity": 0,
            "createdAt": "2024-01-15T10:25:00Z",
            "updatedAt": null,
            "quantityUnit": "g"
        },
        {
            "id": "7",
            "name": "BBQ Chicken Pizza",
            "description": "Smoky BBQ sauce, grilled chicken, red onions, and cilantro",
            "price": 15.99,
            "discountPrice": 12.99,
            "imageUrl": "https://images.unsplash.com/photo-1565299624946-b28f40a0ae38?w=400",
            "category": "pizza",
            "isAvailable": true,
            "stockQuantity": 24500,
            "createdAt": "2024-01-15T10:30:00Z",
            "updatedAt": null,
            "quantityUnit": "g"
        },
        {
            "id": "8",
            "name": "Classic Cheeseburger",
            "description": "Beef patty with cheese, lettuce, tomato, pickles, and special sauce",
            "price": 10.99,
            "discountPrice": null,
            "imageUrl": "https://images.unsplash.com/photo-1568901346375-23c9450c58cd?w=400",
            "category": "burger",
            "isAvailable": true,
            "stockQuantity": 12600,
            "createdAt": "2024-01-15T10:35:00Z",
            "updatedAt": null,
            "quantityUnit": "g"
        },
        {
            "id": "9",
            "name": "Greek Salad",
            "description": "Fresh vegetables, feta cheese, olives, and Greek dressing",
            "price": 9.99,
            "discountPrice": null,
            "imageUrl": "https://images.unsplash.com/photo-1546069901-ba9599a7e63c?w=400",
            "category": "salad",
            "isAvailable": true,
            "stockQuantity": 22400,
            "createdAt": "2024-01-15T10:40:00Z",
            "updatedAt": null,
            "quantityUnit": "g"
        },
        {
            "id": "10",
            "name": "Spaghetti Bolognese",
            "description": "Classic Italian pasta with rich meat sauce",
            "price": 12.99,
            "discountPrice": null,
            "imageUrl": "https://images.unsplash.com/photo-1551183053-bf91a1d81141?w=400",
            "category": "pasta",
            "isAvailable": true,
            "stockQuantity": 24750,
            "createdAt": "2024-01-15T10:45:00Z",
            "updatedAt": null,
            "quantityUnit": "g"
        },
        {
            "id": "11",
            "name": "Tiramisu",
            "description": "Classic Italian dessert with coffee-soaked ladyfingers and mascarpone",
            "price": 7.99,
            "discountPrice": 5.99,
            "imageUrl": "https://images.unsplash.com/photo-1571877227200-a0d98ea607e9?w=400",
            "category": "dessert",
            "isAvailable": true,
            "stockQuantity": 4500,
            "createdAt": "2024-01-15T10:50:00Z",
            "updatedAt": null,
            "quantityUnit": "g"
        },
        {
            "id": "12",
            "name": "Veggie Supreme Pizza",
            "description": "Loaded with bell peppers, mushrooms, onions, olives, and cheese",
            "price": 13.99,
            "discountPrice": null,
            "imageUrl": "https://images.unsplash.com/photo-1513104890138-7c749659a591?w=400",
            "category": "pizza",
            "isAvailable": true,
            "stockQuantity": 29400,
            "createdAt": "2024-01-15T10:55:00Z",
            "updatedAt": null,
            "quantityUnit": "g"
        },
        {
            "id": "13",
            "name": "Fresh Orange Juice",
            "description": "Freshly squeezed orange juice, served cold",
            "price": 4.99,
            "discountPrice": null,
            "imageUrl": null,
            "category": "drink",
            "isAvailable": true,
            "stockQuantity": 100000,
            "createdAt": "2024-01-15T11:00:00Z",
            "updatedAt": null,
            "quantityUnit": "ml"
        },
        {
            "id": "14",
            "name": "Iced Coffee",
            "description": "Cold brew coffee with ice, perfect for hot days",
            "price": 5.99,
            "discountPrice": 4.99,
            "imageUrl": null,
            "category": "drink",
            "isAvailable": true,
            "stockQuantity": 80000,
            "createdAt": "2024-01-15T11:05:00Z",
            "updatedAt": null,
            "quantityUnit": "ml"
        },
        {
            "id": "15",
            "name": "Lemonade",
            "description": "Refreshing homemade lemonade with fresh lemons",
            "price": 3.99,
            "discountPrice": null,
            "imageUrl": null,
            "category": "drink",
            "isAvailable": true,
            "stockQuantity": 120000,
            "createdAt": "2024-01-15T11:10:00Z",
            "updatedAt": null,
            "quantityUnit": "ml"
        },
        {
            "id": "16",
            "name": "Caprese Salad",
            "description": "Fresh mozzarella, tomatoes, and basil with balsamic glaze",
            "price": 10.99,
            "discountPrice": null,
            "imageUrl": null,
            "category": "salad",
            "isAvailable": true,
            "stockQuantity": 16800,
            "createdAt": "2024-01-15T11:15:00Z",
            "updatedAt": null,
            "quantityUnit": "g"
        },
        {
            "id": "17",
            "name": "Fettuccine Alfredo",
            "description": "Creamy fettuccine pasta with parmesan cheese and butter",
            "price": 14.99,
            "discountPrice": null,
            "imageUrl": null,
            "category": "pasta",
            "isAvailable": true,
            "stockQuantity": 22500,
            "createdAt": "2024-01-15T11:20:00Z",
            "updatedAt": null,
            "quantityUnit": "g"
        },
        {
            "id": "18",
            "name": "Bacon Cheeseburger",
            "description": "Beef patty with crispy bacon, cheese, and special sauce",
            "price": 12.99,
            "discountPrice": null,
            "imageUrl": null,
            "category": "burger",
            "isAvailable": true,
            "stockQuantity": 10640,
            "createdAt": "2024-01-15T11:25:00Z",
            "updatedAt": null,
            "quantityUnit": "g"
        },
        {
            "id": "19",
            "name": "Cheesecake",
            "description": "Creamy New York style cheesecake with berry topping",
            "price": 8.99,
            "discountPrice": null,
            "imageUrl": null,
            "category": "dessert",
            "isAvailable": true,
            "stockQuantity": 5400,
            "createdAt": "2024-01-15T11:30:00Z",
            "updatedAt": null,
            "quantityUnit": "g"
        },
        {
            "id": "20",
            "name": "Hawaiian Pizza",
            "description": "Pizza with ham, pineapple, and mozzarella cheese",
            "price": 13.99,
            "discountPrice": 11.99,
            "imageUrl": null,
            "category": "pizza",
            "isAvailable": true,
            "stockQuantity": 19600,
            "createdAt": "2024-01-15T11:35:00Z",
            "updatedAt": null,
            "quantityUnit": "g"
        },
        {
            "id": "21",
            "name": "Sparkling Water",
            "description": "Refreshing sparkling water with a slice of lemon",
            "price": 2.99,
            "discountPrice": null,
            "imageUrl": null,
            "category": "drink",
            "isAvailable": true,
            "stockQuantity": 200000,
            "createdAt": "2024-01-15T11:40:00Z",
            "updatedAt": null,
            "quantityUnit": "ml"
        },
        {
            "id": "22",
            "name": "Chocolate Milkshake",
            "description": "Rich chocolate milkshake topped with whipped cream",
            "price": 6.99,
            "discountPrice": null,
            "imageUrl": null,
            "category": "drink",
            "isAvailable": true,
            "stockQuantity": 45000,
            "createdAt": "2024-01-15T11:45:00Z",
            "updatedAt": null,
            "quantityUnit": "ml"
        },
        {
            "id": "23",
            "name": "Caesar Pasta",
            "description": "Pasta with Caesar dressing, parmesan, and croutons",
            "price": 13.99,
            "discountPrice": null,
            "imageUrl": null,
            "category": "pasta",
            "isAvailable": true,
            "stockQuantity": 18000,
            "createdAt": "2024-01-15T11:50:00Z",
            "updatedAt": null,
            "quantityUnit": "g"
        },
        {
            "id": "24",
            "name": "Apple Pie",
            "description": "Homemade apple pie with cinnamon and vanilla ice cream",
            "price": 7.99,
            "discountPrice": 6.49,
            "imageUrl": null,
            "category": "dessert",
            "isAvailable": true,
            "stockQuantity": 3600,
            "createdAt": "2024-01-15T11:55:00Z",
            "updatedAt": null,
            "quantityUnit": "g"
        },
        {
            "id": "25",
            "name": "Chicken Wings",
            "description": "Crispy fried chicken wings with your choice of sauce",
            "price": 9.99,
            "discountPrice": null,
            "imageUrl": null,
            "category": "appetizer",
            "isAvailable": true,
            "stockQuantity": 9900,
            "createdAt": "2024-01-15T12:00:00Z",
            "updatedAt": null,
            "quantityUnit": "g"
        },
        {
            "id": "26",
            "name": "Mozzarella Sticks",
            "description": "Breaded mozzarella sticks served with marinara sauce",
            "price": 7.99,
            "discountPrice": 6.99,
            "imageUrl": null,
            "category": "appetizer",
            "isAvailable": true,
            "stockQuantity": 12600,
            "createdAt": "2024-01-15T12:05:00Z",
            "updatedAt": null,
            "quantityUnit": "g"
        },
        {
            "id": "27",
            "name": "Tomato Soup",
            "description": "Creamy tomato soup with fresh basil and croutons",
            "price": 6.99,
            "discountPrice": null,
            "imageUrl": null,
            "category": "soup",
            "isAvailable": true,
            "stockQuantity": 40500,
            "createdAt": "2024-01-15T12:10:00Z",
            "updatedAt": null,
            "quantityUnit": "ml"
        },
        {
            "id": "28",
            "name": "Chicken Noodle Soup",
            "description": "Classic chicken noodle soup with vegetables",
            "price": 7.99,
            "discountPrice": null,
            "imageUrl": null,
            "category": "soup",
            "isAvailable": true,
            "stockQuantity": 33750,
            "createdAt": "2024-01-15T12:15:00Z",
            "updatedAt": null,
            "quantityUnit": "ml"
        },
        {
            "id": "29",
            "name": "Club Sandwich",
            "description": "Triple-decker sandwich with turkey, bacon, lettuce, and tomato",
            "price": 10.99,
            "discountPrice": null,
            "imageUrl": null,
            "category": "sandwich",
            "isAvailable": true,
            "stockQuantity": 11000,
            "createdAt": "2024-01-15T12:20:00Z",
            "updatedAt": null,
            "quantityUnit": "g"
        },
        {
            "id": "30",
            "name": "Grilled Cheese Sandwich",
            "description": "Classic grilled cheese with cheddar and mozzarella",
            "price": 6.99,
            "discountPrice": null,
            "imageUrl": null,
            "category": "sandwich",
            "isAvailable": true,
            "stockQuantity": 14300,
            "createdAt": "2024-01-15T12:25:00Z",
            "updatedAt": null,
            "quantityUnit": "g"
        },
        {
            "id": "31",
            "name": "Pancakes",
            "description": "Fluffy pancakes served with maple syrup and butter",
            "price": 8.99,
            "discountPrice": null,
            "imageUrl": null,
            "category": "breakfast",
            "isAvailable": true,
            "stockQuantity": 14000,
            "createdAt": "2024-01-15T12:30:00Z",
            "updatedAt": null,
            "quantityUnit": "g"
        },
        {
            "id": "32",
            "name": "French Toast",
            "description": "Golden French toast with powdered sugar and berries",
            "price": 9.99,
            "discountPrice": 8.49,
            "imageUrl": null,
            "category": "breakfast",
            "isAvailable": true,
            "stockQuantity": 12250,
            "createdAt": "2024-01-15T12:35:00Z",
            "updatedAt": null,
            "quantityUnit": "g"
        },
        {
            "id": "33",
            "name": "Eggs Benedict",
            "description": "Poached eggs on English muffin with hollandaise sauce",
            "price": 11.99,
            "discountPrice": null,
            "imageUrl": null,
            "category": "breakfast",
            "isAvailable": true,
            "stockQuantity": 10500,
            "createdAt": "2024-01-15T12:40:00Z",
            "updatedAt": null,
            "quantityUnit": "g"
        }
    ]
}
